pyppspec/__init__.py
pyppspec/devices.py
pyppspec/pumpprobe.py
pyppspec-0.1.6.1.dist-info/LICENSE
pyppspec-0.1.6.1.dist-info/METADATA
pyppspec-0.1.6.1.dist-info/WHEEL
pyppspec-0.1.6.1.dist-info/top_level.txt
pyppspec-0.1.6.1.dist-info/RECORD
